tafver_metars/__init__.py
tafver_metars/__main__.py
tafver_metars/console.py
tafver_metars/download.py
tafver_metars/exceptions.py
tafver_metars/logger.py
tafver_metars/sanitize.py
tafver_metars-0.4.1.dist-info/entry_points.txt
tafver_metars-0.4.1.dist-info/LICENSE
tafver_metars-0.4.1.dist-info/WHEEL
tafver_metars-0.4.1.dist-info/METADATA
tafver_metars-0.4.1.dist-info/RECORD
