Metadata-Version: 2.1
Name: tafver-metars
Version: 0.4.1
Summary: Download and formating METAR's and TAF's as an input for TAF-VER software verificator.
Home-page: https://github.com/diego-garro/tafver-metars
License: MIT
Author: diego-garro
Author-email: diego.garromolina@yahoo.com
Requires-Python: >=3.6,<4.0
Classifier: License :: OSI Approved :: MIT License
Classifier: Programming Language :: Python :: 3
Classifier: Programming Language :: Python :: 3.6
Classifier: Programming Language :: Python :: 3.7
Classifier: Programming Language :: Python :: 3.8
Classifier: Programming Language :: Python :: 3.9
Requires-Dist: bs4 (>=0.0.1,<0.0.2)
Requires-Dist: click (>=7.1.2,<8.0.0)
Requires-Dist: metar (>=1.8.0,<2.0.0)
Requires-Dist: requests (>=2.25.1,<3.0.0)
Requires-Dist: rich (>=9.13.0,<10.0.0)
Project-URL: Repository, https://github.com/diego-garro/tafver-metars
